kynaylibs/__init__.py
kynaylibs/version.py
kynaylibs/nan/__init__.py
kynaylibs/nan/load.py
kynaylibs/nan/log.py
kynaylibs/nan/utils/PyroHelpers.py
kynaylibs/nan/utils/__init__.py
kynaylibs/nan/utils/adminHelpers.py
kynaylibs/nan/utils/ai.py
kynaylibs/nan/utils/aiohttp_helper.py
kynaylibs/nan/utils/basic.py
kynaylibs/nan/utils/constants.py
kynaylibs/nan/utils/function.py
kynaylibs/nan/utils/get_id.py
kynaylibs/nan/utils/http.py
kynaylibs/nan/utils/inline.py
kynaylibs/nan/utils/interval.py
kynaylibs/nan/utils/misc.py
kynaylibs/nan/utils/parser.py
kynaylibs/nan/utils/pilter.py
kynaylibs/nan/utils/tools.py
kynaylibs/nan/utils/unpack.py
kynaylibs/nan/utils/utility.py
kynaylibs/nan/utils/db/__init__.py
kynaylibs/nan/utils/db/permit.py
nabeuserbot_pylibs-1.0.0.dist-info/LICENSE
nabeuserbot_pylibs-1.0.0.dist-info/METADATA
nabeuserbot_pylibs-1.0.0.dist-info/WHEEL
nabeuserbot_pylibs-1.0.0.dist-info/top_level.txt
nabeuserbot_pylibs-1.0.0.dist-info/RECORD
